charlcd/__init__.py
charlcd/buffered.py
charlcd/direct.py
charlcd/handler.py
charlcd/virtual_buffered.py
charlcd/virtual_direct.py
charlcd/abstract/__init__.py
charlcd/abstract/buffered_interface.py
charlcd/abstract/direct_interface.py
charlcd/abstract/flush_event_interface.py
charlcd/abstract/lcd.py
charlcd/abstract/lcd_virtual.py
charlcd/demos/__init__.py
charlcd/demos/lcd_buffered.py
charlcd/demos/lcd_direct.py
charlcd/demos/lcd_handler.py
charlcd/demos/lcd_virtual_buffered.py
charlcd/demos/lcd_virtual_direct.py
charlcd/demos/lcd_wifi_content.py
charlcd/demos/lcd_wifi_direct.py
charlcd/drivers/__init__.py
charlcd/drivers/base.py
charlcd/drivers/gpio.py
charlcd/drivers/i2c.py
charlcd/drivers/i2cm.py
charlcd/drivers/null.py
charlcd/drivers/null_events.py
charlcd/drivers/wifi_content.py
charlcd/drivers/wifi_direct.py
piader_1_1/__init__.py
piader_1_1/bomb.py
piader_1_1/ctrl_keyboard.py
piader_1_1/enemy.py
piader_1_1/event_server.py
piader_1_1/game.py
piader_1_1/item.py
piader_1_1/local_key.py
piader_1_1/missile.py
piader_1_1/player.py
charlcd-0.7.1.dist-info/LICENSE
charlcd-0.7.1.dist-info/METADATA
charlcd-0.7.1.dist-info/WHEEL
charlcd-0.7.1.dist-info/top_level.txt
charlcd-0.7.1.dist-info/RECORD
