Metadata-Version: 2.1
Name: charlcd
Version: 0.7.1
Summary: charlcd is a handler for char lcds Hitachi HD44780 @ Raspberry Pi.
Home-page: https://bitbucket.org/kosci/charlcd.git
Author: Bartosz Kościów
Author-email: kosci1@gmail.com
License: MIT
Keywords: charlcd,raspberry pi,hd44780,44780,hitachi,hd 44780,lcd,char lcd
Platform: UNKNOWN
Classifier: Development Status :: 4 - Beta
Classifier: Environment :: Console
Classifier: Intended Audience :: Developers
Classifier: Natural Language :: English
Classifier: License :: OSI Approved :: MIT License
Classifier: Operating System :: OS Independent
Classifier: Programming Language :: Python
Classifier: Programming Language :: Python :: 2.7
Classifier: Programming Language :: Python :: 3
Classifier: Topic :: Software Development :: Libraries :: Python Modules
Classifier: Topic :: Home Automation
